fortressofsolitude/__init__.py
fortressofsolitude/__main__.py
fortressofsolitude/comic.py
fortressofsolitude/comic_release_url_builder.py
fortressofsolitude/date.py
fortressofsolitude/web_scraper.py
fortressofsolitude-0.1.0.dist-info/WHEEL
fortressofsolitude-0.1.0.dist-info/METADATA
fortressofsolitude-0.1.0.dist-info/RECORD
