Metadata-Version: 2.1
Name: fortressofsolitude
Version: 0.1.0
Summary: A client to retrieve new releases of comic books, filterable by publisher and format.
Author: Aaron Steed
Author-email: asteed7@gmail.com
Requires-Python: >=3.9,<4.0
Classifier: Programming Language :: Python :: 3
Classifier: Programming Language :: Python :: 3.9
Classifier: Programming Language :: Python :: 3.10
Classifier: Programming Language :: Python :: 3.11
Requires-Dist: beautifulsoup4 (==4.11.1)
Requires-Dist: pyyaml (>=6.0,<7.0)
Requires-Dist: requests (==2.28.1)
